clip_similarwords/__init__.py
clip_similarwords/clip_danbooru_similarwords.py
clip_similarwords/clip_danbooru_similarwords_all.pt
clip_similarwords/clip_danbooru_similarwords_gen.py
clip_similarwords/clip_similarities_bak.py
clip_similarwords/clip_similarwords.py
clip_similarwords/clip_similarwords_all.pt
clip_similarwords/clip_similarwords_gen.py
clip_similarwords/clip_similarwords_gen_bak.py
clip_similarwords/clip_similarwords_old.py
clip_similarwords/clip_synsets_similarwords.py
clip_similarwords/clip_synsets_similarwords_all.pt
clip_similarwords/clip_synsets_similarwords_gen.py
clip_similarwords-0.0.4.1.data/scripts/clip-danbooru-similarwords
clip_similarwords-0.0.4.1.data/scripts/clip-similarwords
clip_similarwords-0.0.4.1.data/scripts/clip-synsets-similarwords
clip_similarwords-0.0.4.1.dist-info/LICENSE
clip_similarwords-0.0.4.1.dist-info/METADATA
clip_similarwords-0.0.4.1.dist-info/WHEEL
clip_similarwords-0.0.4.1.dist-info/top_level.txt
clip_similarwords-0.0.4.1.dist-info/RECORD
