Metadata-Version: 2.1
Name: clip-similarwords
Version: 0.0.4.1
Summary: finding similar 1-token words on OpenAI's CLIP.
Home-page: https://github.com/nazodane/clip_similarwords
Author: Toshimitsu Kimura
Author-email: lovesyao@gmail.com
License: MIT
Keywords: clip
Classifier: Development Status :: 3 - Alpha
Classifier: Topic :: Scientific/Engineering :: Artificial Intelligence
Classifier: License :: OSI Approved :: MIT License
Classifier: Programming Language :: Python :: 3.10
Classifier: Operating System :: POSIX :: Linux
Classifier: Environment :: GPU :: NVIDIA CUDA :: 11.7
Classifier: Intended Audience :: Science/Research
Requires-Python: >=3.10.0
License-File: LICENSE
